AUTHORS
CHANGELOG
CONTRIBUTING.rst
INSTALL
LICENSE
MANIFEST.in
README.rst
VERSION
setup.cfg
setup.py
django_aggtrigg/.coverage
django_aggtrigg/__init__.py
django_aggtrigg/admin.py
django_aggtrigg/dbcommands.py
django_aggtrigg/models.py
django_aggtrigg/tests.py
django_aggtrigg/tool.py
django_aggtrigg/tool_tests.py
django_aggtrigg/util.py
django_aggtrigg/util_tests.py
django_aggtrigg/views.py
django_aggtrigg.egg-info/PKG-INFO
django_aggtrigg.egg-info/SOURCES.txt
django_aggtrigg.egg-info/dependency_links.txt
django_aggtrigg.egg-info/not-zip-safe
django_aggtrigg.egg-info/requires.txt
django_aggtrigg.egg-info/top_level.txt
django_aggtrigg/databases/__init__.py
django_aggtrigg/databases/pg.py
django_aggtrigg/databases/pg_tests.py
django_aggtrigg/databases/templates/pg_create_table.sql
django_aggtrigg/databases/templates/pg_function.sql
django_aggtrigg/databases/templates/pg_function_create.sql
django_aggtrigg/databases/templates/pg_function_delete.sql
django_aggtrigg/databases/templates/pg_function_insert.sql
django_aggtrigg/databases/templates/pg_function_update.sql
django_aggtrigg/databases/templates/pg_init.sql
django_aggtrigg/management/__init__.py
django_aggtrigg/management/djutil.py
django_aggtrigg/management/commands/__init__.py
django_aggtrigg/management/commands/aggtrigg_check.py
django_aggtrigg/management/commands/aggtrigg_create.py
django_aggtrigg/management/commands/aggtrigg_drop.py
django_aggtrigg/management/commands/aggtrigg_initialize.py