Metadata-Version: 1.1
Name: django-aggtrigg
Version: 0.6.6
Summary: Django complementary index definition and management.
Home-page: https://django-aggtrigg.readthedocs.org/
Author: Rodolphe Quiédeville
Author-email: rodolphe@quiedeville.org
License: BSD
Keywords: aggregat trigger count min maxdatabase index postgresql django
Platform: UNKNOWN
Classifier: Programming Language :: Python :: 2.7
Classifier: Development Status :: 3 - Alpha
Classifier: Framework :: Django
Classifier: License :: OSI Approved :: BSD License
